devtools_whitespace/__init__.py
devtools_whitespace-1.0.1.dist-info/METADATA
devtools_whitespace-1.0.1.dist-info/WHEEL
devtools_whitespace-1.0.1.dist-info/top_level.txt
devtools_whitespace-1.0.1.dist-info/RECORD
